almalinux/gitutils/__init__.py
almalinux/gitutils/blob_upload.py
almalinux/gitutils/common.py
almalinux/gitutils/errors.py
almalinux/gitutils/get_sources.py
almalinux_git_utils-0.0.1.dist-info/LICENSE
almalinux_git_utils-0.0.1.dist-info/METADATA
almalinux_git_utils-0.0.1.dist-info/WHEEL
almalinux_git_utils-0.0.1.dist-info/entry_points.txt
almalinux_git_utils-0.0.1.dist-info/top_level.txt
almalinux_git_utils-0.0.1.dist-info/RECORD
