Metadata-Version: 2.1
Name: almalinux-git-utils
Version: 0.0.1
Summary: Utilities for working with the AlmaLinux OS Git server
Home-page: https://git.almalinux.org/almalinux/almalinux-git-utils
Author: Eugene Zamriy
Author-email: ezamriy@almalinux.org
License: UNKNOWN
Project-URL: Bug Tracker, https://git.almalinux.org/almalinux/almalinux-git-utils/issues
Platform: UNKNOWN
Classifier: Programming Language :: Python :: 3
Classifier: License :: OSI Approved :: GNU General Public License v3 or later (GPLv3+)
Classifier: Operating System :: OS Independent
Requires-Python: >=3.6
License-File: LICENSE
Requires-Dist: boto3 (>=1.15.15)
Requires-Dist: requests (>=2.20.0)
